jesse_ftx_futures/__init__.py
jesse_ftx_futures-0.1.0.dist-info/LICENSE
jesse_ftx_futures-0.1.0.dist-info/METADATA
jesse_ftx_futures-0.1.0.dist-info/WHEEL
jesse_ftx_futures-0.1.0.dist-info/top_level.txt
jesse_ftx_futures-0.1.0.dist-info/RECORD
