Metadata-Version: 2.1
Name: jesse-ftx-futures
Version: 0.1.0
Summary: FTX Futures driver for Jesse framework
Home-page: https://jesse.trade
Author: Gabri
Author-email: stramaz.com@gmail.com
License: UNKNOWN
Project-URL: Documentation, https://docs.jesse.trade
Project-URL: Say Thanks!, http://jesse.trade/discord
Project-URL: Source, https://github.com/Gabri/ftx-futures-driver
Project-URL: Tracker, https://github.com/Gabri/ftx-futures-driver/issues
Platform: UNKNOWN
Classifier: Programming Language :: Python :: 3
Classifier: License :: OSI Approved :: MIT License
Classifier: Operating System :: OS Independent
Requires-Python: >=3.7
License-File: LICENSE
Requires-Dist: jesse
